<?xml version="1.0" encoding="utf-8" ?>
<dwsync>
<file name="index.html" server="C:/inetpub/wwwroot/sitem/" local="131881468667282653" remote="131881468660000000" />
<file name="index.html" server="C:/inetpub/wwwroot/site/sitem" local="131881468667282653" remote="131881468660000000" />
<file name="index.html" server="C:/inetpub/wwwroot/site/sitem/" local="131881468667282653" remote="131881468660000000" />
<file name="index.html" server="C:/inetpub/wwwroot/site1" local="131881468667282653" remote="131881468660000000" />
<file name="index.html" server="C:/inetpub/wwwroot/site1/" local="131960775440649984" remote="131960775440000000" />
<file name="3d-wallpaper-12_ablmm7l.jpg" server="C:/inetpub/wwwroot/site1/" local="131882156124857044" remote="131882156120000000" />
<file name="3d-wallpaper-12_ablmm7l55.jpg" server="C:/inetpub/wwwroot/site1/" local="131882170288436017" remote="131882170280000000" />
<file name="iletisim.html" server="C:/inetpub/wwwroot/site1/" local="131882182259681712" remote="131882182250000000" />
<file name="hakkimda.html" server="C:/inetpub/wwwroot/site1/" local="131882194877203077" remote="131882194870000000" />
<file name="iletisim_button5.jpg" server="C:/inetpub/wwwroot/site1/" local="131882181631643120" remote="131882181630000000" />
<file name="photo-1517911122989-a8bcd823bed3.jfif" server="C:/inetpub/wwwroot/site1/" local="131882193370560150" remote="131882193370000000" />
<file name="Yazılım Mühendisi VS Bilgisayar Mühendisi- Aralarında Ne Fark Var- - YouTube.mkv" server="C:/inetpub/wwwroot/site1/" local="131882225272207230" remote="131882225270000000" />
<file name="ıslık şarkısı - YouTube.mp3" server="C:/inetpub/wwwroot/site1/" local="131882230230833950" remote="131882230230000000" />
<file name="islik.mp3" server="C:/inetpub/wwwroot/site1/" local="131882230230833950" remote="131882230230000000" />
<file name="c_örnekler.htm" server="C:/inetpub/wwwroot/site1/" local="131949630527231854" remote="131949630520000000" />
<file name="nedir.htm" server="C:/inetpub/wwwroot/site1/" local="131885927764272652" remote="131885927760000000" />
<file name="is_imkanlari.htm" server="C:/inetpub/wwwroot/site1/" local="131885939327169954" remote="131885939320000000" />
<file name="arastirma_alanlari.htm" server="C:/inetpub/wwwroot/site1/" local="131885939805153309" remote="131885939800000000" />
<file name="ne_is_yapar.htm" server="C:/inetpub/wwwroot/site1/" local="131885939821067392" remote="131885939820000000" />
<file name="bilg_bilimcileri.htm" server="C:/inetpub/wwwroot/site1/" local="131885939835157354" remote="131885939830000000" />
</dwsync>